aws_lambda_cors/__init__.py
aws_lambda_cors/utils/__init__.py
aws_lambda_cors/utils/headers.py
aws_lambda_cors/utils/response.py
aws_lambda_cors-0.0.3.dist-info/LICENSE
aws_lambda_cors-0.0.3.dist-info/METADATA
aws_lambda_cors-0.0.3.dist-info/WHEEL
aws_lambda_cors-0.0.3.dist-info/top_level.txt
aws_lambda_cors-0.0.3.dist-info/RECORD
