Metadata-Version: 2.1
Name: aws-lambda-cors
Version: 0.0.3
Summary: An AWS Lambda response package utility
Home-page: https://github.com/adrian-pina/aws-lambda-cors
Author: Adrian Pina
Author-email: adrian@quesadillalab.mx
License: UNKNOWN
Platform: UNKNOWN
Classifier: Programming Language :: Python :: 3
Classifier: License :: OSI Approved :: MIT License
Classifier: Operating System :: OS Independent
Requires-Python: >=3.7
